<?xml version="1.0" encoding="UTF-8"?>
<!DOCTYPE vm
SYSTEM "vm.dtd">
<vm name="FeatureModel" root="">
  <binaryOptions>
    <configurationOption>
      <name>app-text__xpdf-4_04-r1</name>
      <children>
        <options>cmyk</options>
        <options>cups</options>
        <options>fontconfig</options>
        <options>i18n</options>
        <options>icons</options>
        <options>libpaper</options>
        <options>metric</options>
        <options>opi</options>
        <options>png</options>
        <options>textselect</options>
        <options>utils</options>
        <options>verify-sig</options>
      </children>
      <optional>False</optional>
    </configurationOption>
    <configurationOption>
      <name>cmyk</name>
      <parent>app-text__xpdf-4_04-r1</parent>
      <optional>True</optional>
    </configurationOption>
    <configurationOption>
      <name>cups</name>
      <parent>app-text__xpdf-4_04-r1</parent>
      <optional>True</optional>
    </configurationOption>
    <configurationOption>
      <name>fontconfig</name>
      <parent>app-text__xpdf-4_04-r1</parent>
      <optional>True</optional>
    </configurationOption>
    <configurationOption>
      <name>i18n</name>
      <parent>app-text__xpdf-4_04-r1</parent>
      <optional>True</optional>
    </configurationOption>
    <configurationOption>
      <name>icons</name>
      <parent>app-text__xpdf-4_04-r1</parent>
      <optional>True</optional>
    </configurationOption>
    <configurationOption>
      <name>libpaper</name>
      <parent>app-text__xpdf-4_04-r1</parent>
      <optional>True</optional>
    </configurationOption>
    <configurationOption>
      <name>metric</name>
      <parent>app-text__xpdf-4_04-r1</parent>
      <optional>True</optional>
    </configurationOption>
    <configurationOption>
      <name>opi</name>
      <parent>app-text__xpdf-4_04-r1</parent>
      <optional>True</optional>
    </configurationOption>
    <configurationOption>
      <name>png</name>
      <parent>app-text__xpdf-4_04-r1</parent>
      <optional>True</optional>
    </configurationOption>
    <configurationOption>
      <name>textselect</name>
      <parent>app-text__xpdf-4_04-r1</parent>
      <optional>True</optional>
    </configurationOption>
    <configurationOption>
      <name>utils</name>
      <parent>app-text__xpdf-4_04-r1</parent>
      <optional>True</optional>
    </configurationOption>
    <configurationOption>
      <name>verify-sig</name>
      <parent>app-text__xpdf-4_04-r1</parent>
      <optional>True</optional>
    </configurationOption>
  </binaryOptions>
  <numericOptions/>
</vm>
