<?xml version="1.0" encoding="UTF-8"?>
<!DOCTYPE vm
SYSTEM "vm.dtd">
<vm name="FeatureModel" root="">
  <binaryOptions>
    <configurationOption>
      <name>games-arcade__shovel-knight-4_1b-r1</name>
      <children>
        <options>joystick</options>
      </children>
      <optional>False</optional>
    </configurationOption>
    <configurationOption>
      <name>joystick</name>
      <parent>games-arcade__shovel-knight-4_1b-r1</parent>
      <optional>True</optional>
    </configurationOption>
  </binaryOptions>
  <numericOptions/>
</vm>
