<?xml version="1.0" encoding="UTF-8"?>
<!DOCTYPE vm
SYSTEM "vm.dtd">
<vm name="FeatureModel" root="">
  <binaryOptions>
    <configurationOption>
      <name>gnome-extra__libgsf-1_14_50-r1</name>
      <children>
        <options>bzip2</options>
        <options>gtk</options>
        <options>introspection</options>
        <options>test</options>
      </children>
      <optional>False</optional>
    </configurationOption>
    <configurationOption>
      <name>bzip2</name>
      <parent>gnome-extra__libgsf-1_14_50-r1</parent>
      <optional>True</optional>
    </configurationOption>
    <configurationOption>
      <name>gtk</name>
      <parent>gnome-extra__libgsf-1_14_50-r1</parent>
      <optional>True</optional>
    </configurationOption>
    <configurationOption>
      <name>introspection</name>
      <parent>gnome-extra__libgsf-1_14_50-r1</parent>
      <optional>True</optional>
    </configurationOption>
    <configurationOption>
      <name>test</name>
      <parent>gnome-extra__libgsf-1_14_50-r1</parent>
      <optional>True</optional>
    </configurationOption>
  </binaryOptions>
  <numericOptions/>
</vm>
