<?xml version="1.0" encoding="UTF-8"?>
<!DOCTYPE vm
SYSTEM "vm.dtd">
<vm name="FeatureModel" root="">
  <binaryOptions>
    <configurationOption>
      <name>kde-apps__kdesdk-meta-23_04_3</name>
      <children>
        <options>cvs</options>
        <options>git</options>
        <options>mercurial</options>
        <options>perl</options>
        <options>php</options>
        <options>python</options>
        <options>subversion</options>
        <options>webengine</options>
      </children>
      <optional>False</optional>
    </configurationOption>
    <configurationOption>
      <name>cvs</name>
      <parent>kde-apps__kdesdk-meta-23_04_3</parent>
      <optional>True</optional>
    </configurationOption>
    <configurationOption>
      <name>git</name>
      <parent>kde-apps__kdesdk-meta-23_04_3</parent>
      <optional>True</optional>
    </configurationOption>
    <configurationOption>
      <name>mercurial</name>
      <parent>kde-apps__kdesdk-meta-23_04_3</parent>
      <optional>True</optional>
    </configurationOption>
    <configurationOption>
      <name>perl</name>
      <parent>kde-apps__kdesdk-meta-23_04_3</parent>
      <optional>True</optional>
    </configurationOption>
    <configurationOption>
      <name>php</name>
      <parent>kde-apps__kdesdk-meta-23_04_3</parent>
      <optional>True</optional>
    </configurationOption>
    <configurationOption>
      <name>python</name>
      <parent>kde-apps__kdesdk-meta-23_04_3</parent>
      <optional>True</optional>
    </configurationOption>
    <configurationOption>
      <name>subversion</name>
      <parent>kde-apps__kdesdk-meta-23_04_3</parent>
      <optional>True</optional>
    </configurationOption>
    <configurationOption>
      <name>webengine</name>
      <parent>kde-apps__kdesdk-meta-23_04_3</parent>
      <optional>True</optional>
    </configurationOption>
  </binaryOptions>
  <numericOptions/>
</vm>
