<?xml version="1.0" encoding="UTF-8"?>
<!DOCTYPE vm
SYSTEM "vm.dtd">
<vm name="FeatureModel" root="">
  <binaryOptions>
    <configurationOption>
      <name>mail-client__mutt-2_2_10</name>
      <children>
        <options>berkdb</options>
        <options>debug</options>
        <options>doc</options>
        <options>gdbm</options>
        <options>gnutls</options>
        <options>gpgme</options>
        <options>hcache</options>
        <options>idn</options>
        <options>kerberos</options>
        <options>lmdb</options>
        <options>mbox</options>
        <options>nls</options>
        <options>pgp-classic</options>
        <options>prefix</options>
        <options>qdbm</options>
        <options>sasl</options>
        <options>selinux</options>
        <options>slang</options>
        <options>smime-classic</options>
        <options>ssl</options>
        <options>tokyocabinet</options>
        <options>vanilla</options>
      </children>
      <optional>False</optional>
    </configurationOption>
    <configurationOption>
      <name>berkdb</name>
      <parent>mail-client__mutt-2_2_10</parent>
      <optional>True</optional>
    </configurationOption>
    <configurationOption>
      <name>debug</name>
      <parent>mail-client__mutt-2_2_10</parent>
      <optional>True</optional>
    </configurationOption>
    <configurationOption>
      <name>doc</name>
      <parent>mail-client__mutt-2_2_10</parent>
      <optional>True</optional>
    </configurationOption>
    <configurationOption>
      <name>gdbm</name>
      <parent>mail-client__mutt-2_2_10</parent>
      <optional>True</optional>
    </configurationOption>
    <configurationOption>
      <name>gnutls</name>
      <parent>mail-client__mutt-2_2_10</parent>
      <optional>True</optional>
    </configurationOption>
    <configurationOption>
      <name>gpgme</name>
      <parent>mail-client__mutt-2_2_10</parent>
      <children>
        <options>autocrypt</options>
      </children>
      <optional>True</optional>
    </configurationOption>
    <configurationOption>
      <name>autocrypt</name>
      <parent>gpgme</parent>
      <optional>True</optional>
    </configurationOption>
    <configurationOption>
      <name>hcache</name>
      <parent>mail-client__mutt-2_2_10</parent>
      <optional>True</optional>
    </configurationOption>
    <configurationOption>
      <name>idn</name>
      <parent>mail-client__mutt-2_2_10</parent>
      <optional>True</optional>
    </configurationOption>
    <configurationOption>
      <name>kerberos</name>
      <parent>mail-client__mutt-2_2_10</parent>
      <optional>True</optional>
    </configurationOption>
    <configurationOption>
      <name>lmdb</name>
      <parent>mail-client__mutt-2_2_10</parent>
      <optional>True</optional>
    </configurationOption>
    <configurationOption>
      <name>mbox</name>
      <parent>mail-client__mutt-2_2_10</parent>
      <optional>True</optional>
    </configurationOption>
    <configurationOption>
      <name>nls</name>
      <parent>mail-client__mutt-2_2_10</parent>
      <optional>True</optional>
    </configurationOption>
    <configurationOption>
      <name>pgp-classic</name>
      <parent>mail-client__mutt-2_2_10</parent>
      <optional>True</optional>
    </configurationOption>
    <configurationOption>
      <name>prefix</name>
      <parent>mail-client__mutt-2_2_10</parent>
      <optional>True</optional>
    </configurationOption>
    <configurationOption>
      <name>qdbm</name>
      <parent>mail-client__mutt-2_2_10</parent>
      <optional>True</optional>
    </configurationOption>
    <configurationOption>
      <name>sasl</name>
      <parent>mail-client__mutt-2_2_10</parent>
      <children>
        <options>gsasl</options>
      </children>
      <optional>True</optional>
    </configurationOption>
    <configurationOption>
      <name>gsasl</name>
      <parent>sasl</parent>
      <optional>True</optional>
    </configurationOption>
    <configurationOption>
      <name>selinux</name>
      <parent>mail-client__mutt-2_2_10</parent>
      <optional>True</optional>
    </configurationOption>
    <configurationOption>
      <name>slang</name>
      <parent>mail-client__mutt-2_2_10</parent>
      <optional>True</optional>
    </configurationOption>
    <configurationOption>
      <name>smime-classic</name>
      <parent>mail-client__mutt-2_2_10</parent>
      <impliedOptions>
        <options>ssl</options>
      </impliedOptions>
      <optional>True</optional>
    </configurationOption>
    <configurationOption>
      <name>ssl</name>
      <parent>mail-client__mutt-2_2_10</parent>
      <children>
        <options>imap</options>
        <options>pop</options>
        <options>smtp</options>
      </children>
      <optional>True</optional>
    </configurationOption>
    <configurationOption>
      <name>imap</name>
      <parent>ssl</parent>
      <optional>True</optional>
    </configurationOption>
    <configurationOption>
      <name>pop</name>
      <parent>ssl</parent>
      <optional>True</optional>
    </configurationOption>
    <configurationOption>
      <name>smtp</name>
      <parent>ssl</parent>
      <optional>True</optional>
    </configurationOption>
    <configurationOption>
      <name>tokyocabinet</name>
      <parent>mail-client__mutt-2_2_10</parent>
      <optional>True</optional>
    </configurationOption>
    <configurationOption>
      <name>vanilla</name>
      <parent>mail-client__mutt-2_2_10</parent>
      <optional>True</optional>
    </configurationOption>
  </binaryOptions>
  <numericOptions/>
  <booleanConstraints>
    <constraint>(hcache =&gt; ((((berkdb | gdbm) | lmdb) | qdbm) | tokyocabinet))</constraint>
    <constraint>(smime-classic =&gt; !gnutls)</constraint>
    <constraint>(sasl =&gt; ((imap | pop) | smtp))</constraint>
    <constraint>(kerberos =&gt; ((imap | pop) | smtp))</constraint>
  </booleanConstraints>
</vm>
