<?xml version="1.0" encoding="UTF-8"?>
<!DOCTYPE vm
SYSTEM "vm.dtd">
<vm name="FeatureModel" root="">
  <binaryOptions>
    <configurationOption>
      <name>mail-client__claws-mail-4_1_1-r2</name>
      <children>
        <options>archive</options>
        <options>bogofilter</options>
        <options>calendar</options>
        <options>clamav</options>
        <options>dbus</options>
        <options>debug</options>
        <options>doc</options>
        <options>gdata</options>
        <options>gnutls</options>
        <options>imap</options>
        <options>ldap</options>
        <options>litehtml</options>
        <options>nls</options>
        <options>nntp</options>
        <options>notification</options>
        <options>pdf</options>
        <options>perl</options>
        <options>pgp</options>
        <options>rss</options>
        <options>session</options>
        <options>sieve</options>
        <options>spam-report</options>
        <options>spamassassin</options>
        <options>spell</options>
        <options>startup-notification</options>
        <options>svg</options>
        <options>valgrind</options>
        <options>webkit</options>
        <options>xface</options>
      </children>
      <optional>False</optional>
    </configurationOption>
    <configurationOption>
      <name>archive</name>
      <parent>mail-client__claws-mail-4_1_1-r2</parent>
      <optional>True</optional>
    </configurationOption>
    <configurationOption>
      <name>bogofilter</name>
      <parent>mail-client__claws-mail-4_1_1-r2</parent>
      <optional>True</optional>
    </configurationOption>
    <configurationOption>
      <name>calendar</name>
      <parent>mail-client__claws-mail-4_1_1-r2</parent>
      <optional>True</optional>
    </configurationOption>
    <configurationOption>
      <name>clamav</name>
      <parent>mail-client__claws-mail-4_1_1-r2</parent>
      <optional>True</optional>
    </configurationOption>
    <configurationOption>
      <name>dbus</name>
      <parent>mail-client__claws-mail-4_1_1-r2</parent>
      <children>
        <options>networkmanager</options>
      </children>
      <optional>True</optional>
    </configurationOption>
    <configurationOption>
      <name>networkmanager</name>
      <parent>dbus</parent>
      <optional>True</optional>
    </configurationOption>
    <configurationOption>
      <name>debug</name>
      <parent>mail-client__claws-mail-4_1_1-r2</parent>
      <optional>True</optional>
    </configurationOption>
    <configurationOption>
      <name>doc</name>
      <parent>mail-client__claws-mail-4_1_1-r2</parent>
      <optional>True</optional>
    </configurationOption>
    <configurationOption>
      <name>gdata</name>
      <parent>mail-client__claws-mail-4_1_1-r2</parent>
      <optional>True</optional>
    </configurationOption>
    <configurationOption>
      <name>gnutls</name>
      <parent>mail-client__claws-mail-4_1_1-r2</parent>
      <children>
        <options>oauth</options>
      </children>
      <optional>True</optional>
    </configurationOption>
    <configurationOption>
      <name>oauth</name>
      <parent>gnutls</parent>
      <optional>True</optional>
    </configurationOption>
    <configurationOption>
      <name>imap</name>
      <parent>mail-client__claws-mail-4_1_1-r2</parent>
      <optional>True</optional>
    </configurationOption>
    <configurationOption>
      <name>ldap</name>
      <parent>mail-client__claws-mail-4_1_1-r2</parent>
      <optional>True</optional>
    </configurationOption>
    <configurationOption>
      <name>litehtml</name>
      <parent>mail-client__claws-mail-4_1_1-r2</parent>
      <optional>True</optional>
    </configurationOption>
    <configurationOption>
      <name>nls</name>
      <parent>mail-client__claws-mail-4_1_1-r2</parent>
      <optional>True</optional>
    </configurationOption>
    <configurationOption>
      <name>nntp</name>
      <parent>mail-client__claws-mail-4_1_1-r2</parent>
      <optional>True</optional>
    </configurationOption>
    <configurationOption>
      <name>notification</name>
      <parent>mail-client__claws-mail-4_1_1-r2</parent>
      <children>
        <options>libcanberra</options>
        <options>libnotify</options>
      </children>
      <optional>True</optional>
    </configurationOption>
    <configurationOption>
      <name>libcanberra</name>
      <parent>notification</parent>
      <optional>True</optional>
    </configurationOption>
    <configurationOption>
      <name>libnotify</name>
      <parent>notification</parent>
      <optional>True</optional>
    </configurationOption>
    <configurationOption>
      <name>pdf</name>
      <parent>mail-client__claws-mail-4_1_1-r2</parent>
      <optional>True</optional>
    </configurationOption>
    <configurationOption>
      <name>perl</name>
      <parent>mail-client__claws-mail-4_1_1-r2</parent>
      <optional>True</optional>
    </configurationOption>
    <configurationOption>
      <name>pgp</name>
      <parent>mail-client__claws-mail-4_1_1-r2</parent>
      <children>
        <options>smime</options>
      </children>
      <optional>True</optional>
    </configurationOption>
    <configurationOption>
      <name>smime</name>
      <parent>pgp</parent>
      <optional>True</optional>
    </configurationOption>
    <configurationOption>
      <name>rss</name>
      <parent>mail-client__claws-mail-4_1_1-r2</parent>
      <optional>True</optional>
    </configurationOption>
    <configurationOption>
      <name>session</name>
      <parent>mail-client__claws-mail-4_1_1-r2</parent>
      <optional>True</optional>
    </configurationOption>
    <configurationOption>
      <name>sieve</name>
      <parent>mail-client__claws-mail-4_1_1-r2</parent>
      <optional>True</optional>
    </configurationOption>
    <configurationOption>
      <name>spam-report</name>
      <parent>mail-client__claws-mail-4_1_1-r2</parent>
      <optional>True</optional>
    </configurationOption>
    <configurationOption>
      <name>spamassassin</name>
      <parent>mail-client__claws-mail-4_1_1-r2</parent>
      <optional>True</optional>
    </configurationOption>
    <configurationOption>
      <name>spell</name>
      <parent>mail-client__claws-mail-4_1_1-r2</parent>
      <optional>True</optional>
    </configurationOption>
    <configurationOption>
      <name>startup-notification</name>
      <parent>mail-client__claws-mail-4_1_1-r2</parent>
      <optional>True</optional>
    </configurationOption>
    <configurationOption>
      <name>svg</name>
      <parent>mail-client__claws-mail-4_1_1-r2</parent>
      <optional>True</optional>
    </configurationOption>
    <configurationOption>
      <name>valgrind</name>
      <parent>mail-client__claws-mail-4_1_1-r2</parent>
      <optional>True</optional>
    </configurationOption>
    <configurationOption>
      <name>webkit</name>
      <parent>mail-client__claws-mail-4_1_1-r2</parent>
      <optional>True</optional>
    </configurationOption>
    <configurationOption>
      <name>xface</name>
      <parent>mail-client__claws-mail-4_1_1-r2</parent>
      <optional>True</optional>
    </configurationOption>
  </binaryOptions>
  <numericOptions/>
</vm>
