<?xml version="1.0" encoding="UTF-8"?>
<!DOCTYPE vm
SYSTEM "vm.dtd">
<vm name="FeatureModel" root="">
  <binaryOptions>
    <configurationOption>
      <name>media-sound__baudline-1_08-r2</name>
      <children>
        <options>jack</options>
      </children>
      <optional>False</optional>
    </configurationOption>
    <configurationOption>
      <name>jack</name>
      <parent>media-sound__baudline-1_08-r2</parent>
      <optional>True</optional>
    </configurationOption>
  </binaryOptions>
  <numericOptions/>
</vm>
