<?xml version="1.0" encoding="UTF-8"?>
<!DOCTYPE vm
SYSTEM "vm.dtd">
<vm name="FeatureModel" root="">
  <binaryOptions>
    <configurationOption>
      <name>media-video__mpeg-tools-1_5b-r5</name>
      <children>
        <options></options>
      </children>
      <optional>False</optional>
    </configurationOption>
    <configurationOption>
      <name></name>
      <parent>media-video__mpeg-tools-1_5b-r5</parent>
      <optional>True</optional>
    </configurationOption>
  </binaryOptions>
  <numericOptions/>
</vm>
