<?xml version="1.0" encoding="UTF-8"?>
<!DOCTYPE vm
SYSTEM "vm.dtd">
<vm name="FeatureModel" root="">
  <binaryOptions>
    <configurationOption>
      <name>net-print__fax4cups-1_29-r1</name>
      <children>
        <options>abs_or_grp_1</options>
      </children>
      <optional>False</optional>
    </configurationOption>
    <configurationOption>
      <name>abs_or_grp_1</name>
      <parent>net-print__fax4cups-1_29-r1</parent>
      <children>
        <options>efax</options>
        <options>hylafax</options>
        <options>mgetty-fax</options>
      </children>
      <optional>False</optional>
    </configurationOption>
    <configurationOption>
      <name>efax</name>
      <parent>abs_or_grp_1</parent>
      <excludedOptions>
        <options>hylafax</options>
        <options>mgetty-fax</options>
      </excludedOptions>
      <optional>True</optional>
    </configurationOption>
    <configurationOption>
      <name>hylafax</name>
      <parent>abs_or_grp_1</parent>
      <excludedOptions>
        <options>efax</options>
        <options>mgetty-fax</options>
      </excludedOptions>
      <optional>True</optional>
    </configurationOption>
    <configurationOption>
      <name>mgetty-fax</name>
      <parent>abs_or_grp_1</parent>
      <excludedOptions>
        <options>efax</options>
        <options>hylafax</options>
      </excludedOptions>
      <optional>True</optional>
    </configurationOption>
  </binaryOptions>
  <numericOptions/>
</vm>
