<?xml version="1.0" encoding="UTF-8"?>
<!DOCTYPE vm
SYSTEM "vm.dtd">
<vm name="FeatureModel" root="">
  <binaryOptions>
    <configurationOption>
      <name>net-libs__c-client-2007f-r8</name>
      <children>
        <options>chappa</options>
        <options>doc</options>
        <options>ipv6</options>
        <options>kerberos</options>
        <options>pam</options>
        <options>ssl</options>
        <options>static-libs</options>
        <options>topal</options>
      </children>
      <optional>False</optional>
    </configurationOption>
    <configurationOption>
      <name>chappa</name>
      <parent>net-libs__c-client-2007f-r8</parent>
      <optional>True</optional>
    </configurationOption>
    <configurationOption>
      <name>doc</name>
      <parent>net-libs__c-client-2007f-r8</parent>
      <optional>True</optional>
    </configurationOption>
    <configurationOption>
      <name>ipv6</name>
      <parent>net-libs__c-client-2007f-r8</parent>
      <optional>True</optional>
    </configurationOption>
    <configurationOption>
      <name>kerberos</name>
      <parent>net-libs__c-client-2007f-r8</parent>
      <optional>True</optional>
    </configurationOption>
    <configurationOption>
      <name>pam</name>
      <parent>net-libs__c-client-2007f-r8</parent>
      <optional>True</optional>
    </configurationOption>
    <configurationOption>
      <name>ssl</name>
      <parent>net-libs__c-client-2007f-r8</parent>
      <optional>True</optional>
    </configurationOption>
    <configurationOption>
      <name>static-libs</name>
      <parent>net-libs__c-client-2007f-r8</parent>
      <optional>True</optional>
    </configurationOption>
    <configurationOption>
      <name>topal</name>
      <parent>net-libs__c-client-2007f-r8</parent>
      <optional>True</optional>
    </configurationOption>
  </binaryOptions>
  <numericOptions/>
</vm>
