<?xml version="1.0" encoding="UTF-8"?>
<!DOCTYPE vm
SYSTEM "vm.dtd">
<vm name="FeatureModel" root="">
  <binaryOptions>
    <configurationOption>
      <name>net-print__hplip-3_23_5</name>
      <children>
        <options>abs_xor_grp_1</options>
        <options>doc</options>
        <options>fax</options>
        <options>hpcups</options>
        <options>hpijs</options>
        <options>kde</options>
        <options>libnotify</options>
        <options>libusb0</options>
        <options>minimal</options>
        <options>parport</options>
        <options>policykit</options>
        <options>qt5</options>
        <options>scanner</options>
        <options>snmp</options>
        <options>static-ppds</options>
        <options>X</options>
      </children>
      <optional>False</optional>
    </configurationOption>
    <configurationOption>
      <name>abs_xor_grp_1</name>
      <parent>net-print__hplip-3_23_5</parent>
      <children>
        <options>python_single_target_python3_10</options>
        <options>python_single_target_python3_11</options>
      </children>
      <optional>False</optional>
    </configurationOption>
    <configurationOption>
      <name>python_single_target_python3_10</name>
      <parent>abs_xor_grp_1</parent>
      <excludedOptions>
        <options>python_single_target_python3_11</options>
      </excludedOptions>
      <optional>True</optional>
    </configurationOption>
    <configurationOption>
      <name>python_single_target_python3_11</name>
      <parent>abs_xor_grp_1</parent>
      <excludedOptions>
        <options>python_single_target_python3_10</options>
      </excludedOptions>
      <optional>True</optional>
    </configurationOption>
    <configurationOption>
      <name>doc</name>
      <parent>net-print__hplip-3_23_5</parent>
      <optional>True</optional>
    </configurationOption>
    <configurationOption>
      <name>fax</name>
      <parent>net-print__hplip-3_23_5</parent>
      <optional>True</optional>
    </configurationOption>
    <configurationOption>
      <name>hpcups</name>
      <parent>net-print__hplip-3_23_5</parent>
      <optional>True</optional>
    </configurationOption>
    <configurationOption>
      <name>hpijs</name>
      <parent>net-print__hplip-3_23_5</parent>
      <optional>True</optional>
    </configurationOption>
    <configurationOption>
      <name>kde</name>
      <parent>net-print__hplip-3_23_5</parent>
      <optional>True</optional>
    </configurationOption>
    <configurationOption>
      <name>libnotify</name>
      <parent>net-print__hplip-3_23_5</parent>
      <optional>True</optional>
    </configurationOption>
    <configurationOption>
      <name>libusb0</name>
      <parent>net-print__hplip-3_23_5</parent>
      <optional>True</optional>
    </configurationOption>
    <configurationOption>
      <name>minimal</name>
      <parent>net-print__hplip-3_23_5</parent>
      <optional>True</optional>
    </configurationOption>
    <configurationOption>
      <name>parport</name>
      <parent>net-print__hplip-3_23_5</parent>
      <optional>True</optional>
    </configurationOption>
    <configurationOption>
      <name>policykit</name>
      <parent>net-print__hplip-3_23_5</parent>
      <optional>True</optional>
    </configurationOption>
    <configurationOption>
      <name>qt5</name>
      <parent>net-print__hplip-3_23_5</parent>
      <optional>True</optional>
    </configurationOption>
    <configurationOption>
      <name>scanner</name>
      <parent>net-print__hplip-3_23_5</parent>
      <optional>True</optional>
    </configurationOption>
    <configurationOption>
      <name>snmp</name>
      <parent>net-print__hplip-3_23_5</parent>
      <optional>True</optional>
    </configurationOption>
    <configurationOption>
      <name>static-ppds</name>
      <parent>net-print__hplip-3_23_5</parent>
      <optional>True</optional>
    </configurationOption>
    <configurationOption>
      <name>X</name>
      <parent>net-print__hplip-3_23_5</parent>
      <optional>True</optional>
    </configurationOption>
  </binaryOptions>
  <numericOptions/>
</vm>
