<?xml version="1.0" encoding="UTF-8"?>
<!DOCTYPE vm
SYSTEM "vm.dtd">
<vm name="FeatureModel" root="">
  <binaryOptions>
    <configurationOption>
      <name>net-libs__axtls-2_1_5-r102</name>
      <children>
        <options>cgi-lua</options>
        <options>doc</options>
        <options>httpd</options>
        <options>lua_single_target_lua5-1</options>
        <options>lua_single_target_lua5-3</options>
        <options>lua_single_target_lua5-4</options>
        <options>lua_single_target_luajit</options>
        <options>savedconfig</options>
      </children>
      <optional>False</optional>
    </configurationOption>
    <configurationOption>
      <name>cgi-lua</name>
      <parent>net-libs__axtls-2_1_5-r102</parent>
      <impliedOptions>
        <options>httpd</options>
      </impliedOptions>
      <optional>True</optional>
    </configurationOption>
    <configurationOption>
      <name>doc</name>
      <parent>net-libs__axtls-2_1_5-r102</parent>
      <optional>True</optional>
    </configurationOption>
    <configurationOption>
      <name>httpd</name>
      <parent>net-libs__axtls-2_1_5-r102</parent>
      <children>
        <options>cgi-php</options>
        <options>static</options>
      </children>
      <optional>True</optional>
    </configurationOption>
    <configurationOption>
      <name>cgi-php</name>
      <parent>httpd</parent>
      <optional>True</optional>
    </configurationOption>
    <configurationOption>
      <name>static</name>
      <parent>httpd</parent>
      <optional>True</optional>
    </configurationOption>
    <configurationOption>
      <name>lua_single_target_lua5-1</name>
      <parent>net-libs__axtls-2_1_5-r102</parent>
      <optional>True</optional>
    </configurationOption>
    <configurationOption>
      <name>lua_single_target_lua5-3</name>
      <parent>net-libs__axtls-2_1_5-r102</parent>
      <optional>True</optional>
    </configurationOption>
    <configurationOption>
      <name>lua_single_target_lua5-4</name>
      <parent>net-libs__axtls-2_1_5-r102</parent>
      <optional>True</optional>
    </configurationOption>
    <configurationOption>
      <name>lua_single_target_luajit</name>
      <parent>net-libs__axtls-2_1_5-r102</parent>
      <optional>True</optional>
    </configurationOption>
    <configurationOption>
      <name>savedconfig</name>
      <parent>net-libs__axtls-2_1_5-r102</parent>
      <optional>True</optional>
    </configurationOption>
  </binaryOptions>
  <numericOptions/>
  <booleanConstraints>
    <constraint>(cgi-lua =&gt; (((lua_single_target_luajit ^ lua_single_target_lua5-1) ^ lua_single_target_lua5-3) ^ lua_single_target_lua5-4))</constraint>
  </booleanConstraints>
</vm>
