<?xml version="1.0" encoding="UTF-8"?>
<!DOCTYPE vm
SYSTEM "vm.dtd">
<vm name="FeatureModel" root="">
  <binaryOptions>
    <configurationOption>
      <name>sys-apps__s390-tools-2_12_0</name>
      <children>
        <options>cryptsetup</options>
        <options>fuse</options>
        <options>ncurses</options>
        <options>openssl</options>
        <options>pfm</options>
        <options>snmp</options>
        <options>zlib</options>
      </children>
      <optional>False</optional>
    </configurationOption>
    <configurationOption>
      <name>cryptsetup</name>
      <parent>sys-apps__s390-tools-2_12_0</parent>
      <optional>True</optional>
    </configurationOption>
    <configurationOption>
      <name>fuse</name>
      <parent>sys-apps__s390-tools-2_12_0</parent>
      <optional>True</optional>
    </configurationOption>
    <configurationOption>
      <name>ncurses</name>
      <parent>sys-apps__s390-tools-2_12_0</parent>
      <optional>True</optional>
    </configurationOption>
    <configurationOption>
      <name>openssl</name>
      <parent>sys-apps__s390-tools-2_12_0</parent>
      <optional>True</optional>
    </configurationOption>
    <configurationOption>
      <name>pfm</name>
      <parent>sys-apps__s390-tools-2_12_0</parent>
      <optional>True</optional>
    </configurationOption>
    <configurationOption>
      <name>snmp</name>
      <parent>sys-apps__s390-tools-2_12_0</parent>
      <optional>True</optional>
    </configurationOption>
    <configurationOption>
      <name>zlib</name>
      <parent>sys-apps__s390-tools-2_12_0</parent>
      <optional>True</optional>
    </configurationOption>
  </binaryOptions>
  <numericOptions/>
</vm>
