<?xml version="1.0" encoding="UTF-8"?>
<!DOCTYPE vm
SYSTEM "vm.dtd">
<vm name="FeatureModel" root="">
  <binaryOptions>
    <configurationOption>
      <name>sys-devel__clang-common-16_0_6-r2</name>
      <children>
        <options>default-compiler-rt</options>
        <options>default-libcxx</options>
        <options>default-lld</options>
        <options>hardened</options>
        <options>llvm-libunwind</options>
        <options>stricter</options>
        <options>verify-sig</options>
      </children>
      <optional>False</optional>
    </configurationOption>
    <configurationOption>
      <name>default-compiler-rt</name>
      <parent>sys-devel__clang-common-16_0_6-r2</parent>
      <optional>True</optional>
    </configurationOption>
    <configurationOption>
      <name>default-libcxx</name>
      <parent>sys-devel__clang-common-16_0_6-r2</parent>
      <optional>True</optional>
    </configurationOption>
    <configurationOption>
      <name>default-lld</name>
      <parent>sys-devel__clang-common-16_0_6-r2</parent>
      <optional>True</optional>
    </configurationOption>
    <configurationOption>
      <name>hardened</name>
      <parent>sys-devel__clang-common-16_0_6-r2</parent>
      <optional>True</optional>
    </configurationOption>
    <configurationOption>
      <name>llvm-libunwind</name>
      <parent>sys-devel__clang-common-16_0_6-r2</parent>
      <optional>True</optional>
    </configurationOption>
    <configurationOption>
      <name>stricter</name>
      <parent>sys-devel__clang-common-16_0_6-r2</parent>
      <optional>True</optional>
    </configurationOption>
    <configurationOption>
      <name>verify-sig</name>
      <parent>sys-devel__clang-common-16_0_6-r2</parent>
      <optional>True</optional>
    </configurationOption>
  </binaryOptions>
  <numericOptions/>
</vm>
