<?xml version="1.0" encoding="UTF-8"?>
<!DOCTYPE vm
SYSTEM "vm.dtd">
<vm name="FeatureModel" root="">
  <binaryOptions>
    <configurationOption>
      <name>sys-libs__tevent-0_13_0</name>
      <children>
        <options>abi_mips_n32</options>
        <options>abi_mips_n64</options>
        <options>abi_mips_o32</options>
        <options>abi_s390_32</options>
        <options>abi_s390_64</options>
        <options>abi_x86_32</options>
        <options>abi_x86_64</options>
        <options>abi_x86_x32</options>
        <options>abs_xor_grp_1</options>
        <options>python</options>
        <options>test</options>
      </children>
      <optional>False</optional>
    </configurationOption>
    <configurationOption>
      <name>abi_mips_n32</name>
      <parent>sys-libs__tevent-0_13_0</parent>
      <optional>True</optional>
    </configurationOption>
    <configurationOption>
      <name>abi_mips_n64</name>
      <parent>sys-libs__tevent-0_13_0</parent>
      <optional>True</optional>
    </configurationOption>
    <configurationOption>
      <name>abi_mips_o32</name>
      <parent>sys-libs__tevent-0_13_0</parent>
      <optional>True</optional>
    </configurationOption>
    <configurationOption>
      <name>abi_s390_32</name>
      <parent>sys-libs__tevent-0_13_0</parent>
      <optional>True</optional>
    </configurationOption>
    <configurationOption>
      <name>abi_s390_64</name>
      <parent>sys-libs__tevent-0_13_0</parent>
      <optional>True</optional>
    </configurationOption>
    <configurationOption>
      <name>abi_x86_32</name>
      <parent>sys-libs__tevent-0_13_0</parent>
      <optional>True</optional>
    </configurationOption>
    <configurationOption>
      <name>abi_x86_64</name>
      <parent>sys-libs__tevent-0_13_0</parent>
      <optional>True</optional>
    </configurationOption>
    <configurationOption>
      <name>abi_x86_x32</name>
      <parent>sys-libs__tevent-0_13_0</parent>
      <optional>True</optional>
    </configurationOption>
    <configurationOption>
      <name>abs_xor_grp_1</name>
      <parent>sys-libs__tevent-0_13_0</parent>
      <children>
        <options>python_single_target_python3_10</options>
        <options>python_single_target_python3_11</options>
      </children>
      <optional>False</optional>
    </configurationOption>
    <configurationOption>
      <name>python_single_target_python3_10</name>
      <parent>abs_xor_grp_1</parent>
      <excludedOptions>
        <options>python_single_target_python3_11</options>
      </excludedOptions>
      <optional>True</optional>
    </configurationOption>
    <configurationOption>
      <name>python_single_target_python3_11</name>
      <parent>abs_xor_grp_1</parent>
      <excludedOptions>
        <options>python_single_target_python3_10</options>
      </excludedOptions>
      <optional>True</optional>
    </configurationOption>
    <configurationOption>
      <name>python</name>
      <parent>sys-libs__tevent-0_13_0</parent>
      <optional>True</optional>
    </configurationOption>
    <configurationOption>
      <name>test</name>
      <parent>sys-libs__tevent-0_13_0</parent>
      <optional>True</optional>
    </configurationOption>
  </binaryOptions>
  <numericOptions/>
</vm>
