<?xml version="1.0" encoding="UTF-8"?>
<!DOCTYPE vm
SYSTEM "vm.dtd">
<vm name="FeatureModel" root="">
  <binaryOptions>
    <configurationOption>
      <name>x11-wm__fvwm-2_6_9</name>
      <children>
        <options>bidi</options>
        <options>debug</options>
        <options>doc</options>
        <options>lock</options>
        <options>netpbm</options>
        <options>nls</options>
        <options>perl</options>
        <options>png</options>
        <options>readline</options>
        <options>stroke</options>
        <options>svg</options>
        <options>tk</options>
        <options>truetype</options>
        <options>vanilla</options>
        <options>xinerama</options>
      </children>
      <optional>False</optional>
    </configurationOption>
    <configurationOption>
      <name>bidi</name>
      <parent>x11-wm__fvwm-2_6_9</parent>
      <optional>True</optional>
    </configurationOption>
    <configurationOption>
      <name>debug</name>
      <parent>x11-wm__fvwm-2_6_9</parent>
      <optional>True</optional>
    </configurationOption>
    <configurationOption>
      <name>doc</name>
      <parent>x11-wm__fvwm-2_6_9</parent>
      <optional>True</optional>
    </configurationOption>
    <configurationOption>
      <name>lock</name>
      <parent>x11-wm__fvwm-2_6_9</parent>
      <optional>True</optional>
    </configurationOption>
    <configurationOption>
      <name>netpbm</name>
      <parent>x11-wm__fvwm-2_6_9</parent>
      <optional>True</optional>
    </configurationOption>
    <configurationOption>
      <name>nls</name>
      <parent>x11-wm__fvwm-2_6_9</parent>
      <optional>True</optional>
    </configurationOption>
    <configurationOption>
      <name>perl</name>
      <parent>x11-wm__fvwm-2_6_9</parent>
      <optional>True</optional>
    </configurationOption>
    <configurationOption>
      <name>png</name>
      <parent>x11-wm__fvwm-2_6_9</parent>
      <optional>True</optional>
    </configurationOption>
    <configurationOption>
      <name>readline</name>
      <parent>x11-wm__fvwm-2_6_9</parent>
      <optional>True</optional>
    </configurationOption>
    <configurationOption>
      <name>stroke</name>
      <parent>x11-wm__fvwm-2_6_9</parent>
      <optional>True</optional>
    </configurationOption>
    <configurationOption>
      <name>svg</name>
      <parent>x11-wm__fvwm-2_6_9</parent>
      <optional>True</optional>
    </configurationOption>
    <configurationOption>
      <name>tk</name>
      <parent>x11-wm__fvwm-2_6_9</parent>
      <optional>True</optional>
    </configurationOption>
    <configurationOption>
      <name>truetype</name>
      <parent>x11-wm__fvwm-2_6_9</parent>
      <optional>True</optional>
    </configurationOption>
    <configurationOption>
      <name>vanilla</name>
      <parent>x11-wm__fvwm-2_6_9</parent>
      <optional>True</optional>
    </configurationOption>
    <configurationOption>
      <name>xinerama</name>
      <parent>x11-wm__fvwm-2_6_9</parent>
      <optional>True</optional>
    </configurationOption>
  </binaryOptions>
  <numericOptions/>
</vm>
