<?xml version="1.0" encoding="UTF-8"?>
<!DOCTYPE vm
SYSTEM "vm.dtd">
<vm name="FeatureModel" root="">
  <binaryOptions>
    <configurationOption>
      <name>x11-libs__libXfont2-2_0_6</name>
      <children>
        <options>bzip2</options>
        <options>doc</options>
        <options>truetype</options>
      </children>
      <optional>False</optional>
    </configurationOption>
    <configurationOption>
      <name>bzip2</name>
      <parent>x11-libs__libXfont2-2_0_6</parent>
      <optional>True</optional>
    </configurationOption>
    <configurationOption>
      <name>doc</name>
      <parent>x11-libs__libXfont2-2_0_6</parent>
      <optional>True</optional>
    </configurationOption>
    <configurationOption>
      <name>truetype</name>
      <parent>x11-libs__libXfont2-2_0_6</parent>
      <optional>True</optional>
    </configurationOption>
  </binaryOptions>
  <numericOptions/>
</vm>
